ulda/__init__.py
ulda/ulda.py
ulda-0.1.1.dist-info/LICENSE
ulda-0.1.1.dist-info/METADATA
ulda-0.1.1.dist-info/WHEEL
ulda-0.1.1.dist-info/RECORD
