Metadata-Version: 2.1
Name: ulda
Version: 0.1.1
Summary: Uncorrelated Linear Discriminant Analysis
Home-page: https://github.com/Moran79/ulda-Py
License: BSD3
Author: Siyu Wang
Requires-Python: >=3.9,<4.0
Classifier: Development Status :: 3 - Alpha
Classifier: Intended Audience :: Developers
Classifier: License :: Other/Proprietary License
Classifier: Operating System :: OS Independent
Classifier: Programming Language :: Python :: 3
Classifier: Programming Language :: Python :: 3.9
Classifier: Programming Language :: Python :: 3.10
Classifier: Programming Language :: Python :: 3.11
Classifier: Programming Language :: Python :: 3.12
Classifier: Topic :: Software Development :: Libraries :: Python Modules
Requires-Dist: numpy (>=2.0.0)
Requires-Dist: pandas (>=2.2.2)
Requires-Dist: scikit-learn (>=1.5.1)
Project-URL: Repository, https://github.com/Moran79/ulda-Py
